toast/__init__.py
toast/schema.py
toast/toast_sms_client.py
toast_notification_client-0.0.2.dist-info/LICENSE
toast_notification_client-0.0.2.dist-info/METADATA
toast_notification_client-0.0.2.dist-info/WHEEL
toast_notification_client-0.0.2.dist-info/top_level.txt
toast_notification_client-0.0.2.dist-info/RECORD
