Metadata-Version: 2.1
Name: toast-notification-client
Version: 0.0.2
Summary: Toast cloud Notification RESTful API Client for Python User.
Home-page: https://github.com/dohyungp/toast-notification-client
Author: Dohyung Park
Author-email: dohyung.prk@gmail.com
License: UNKNOWN
Platform: UNKNOWN
Classifier: Programming Language :: Python :: 3
Classifier: License :: OSI Approved :: MIT License
Classifier: Operating System :: OS Independent
Requires-Python: >=3.6
Requires-Dist: requests
Requires-Dist: jsonschema
